Workbook

Sheet Suivi Espace Vente
A1: Suivi Espace-Vente
C3: From INV stock | D3: From INV caisse | E3: From HelloAsso
D4: Chiffre d'affaires - Réel
A5: Date d'inventaire | B5: Coût de revient | C5: CA théorique | D5: Caisse | E5: Carte bancaire | F5: Total encaissé | G5: Bénéfice | H5: Ctrl (si négatif pb) | I5: Source
A7: 02/01/26-08/01/26 | D7: 23.72 | E7: 15 | F7: =SUM(D7:E7) -> 38.72 | I7: INV26-00
A8: 09/01/26-15/01/26 | B8: 44.05 | C8: 121 | D8: 92.4 | E8: 58.5 | F8: =SUM(D8:E8) -> 150.9 | G8: =F8-B8 -> 106.85 | H8: =F8-C8 -> 29.9 | I8: INV26-01
A9: 16/01/26-22/01/26 | B9: 55.32 | C9: 122.5 | D9: 67.7 | E9: 73 | F9: =SUM(D9:E9) -> 140.7 | G9: =F9-B9 -> 85.38 | H9: =F9-C9 -> 18.2 | I9: INV26-02
A10: 23/01/26-29/01/26 | B10: 32.91 | C10: 74.5 | D10: 52.21 | E10: 37 | F10: =SUM(D10:E10) -> 89.21 | G10: =F10-B10 -> 56.3 | H10: =F10-C10 -> 14.71 | I10: INV26-03
A11: 30/01/26-04/02/26 | B11: 26.83 | C11: 63.5 | D11: 21.34 | E11: 22.5 | F11: =SUM(D11:E11) -> 43.84 | G11: =F11-B11 -> 17.01 | H11: =F11-C11 -> -19.66 | I11: INV26-04
A12: 05/02/26-11/02/26 | B12: 29.61 | C12: 59.5 | D12: 23.25 | E12: 38.5 | F12: =SUM(D12:E12) -> 61.75 | G12: =F12-B12 -> 32.14 | H12: =F12-C12 -> 2.25 | I12: INV26-05
A13: 12/02/26 - 18/02/26 | B13: 65.65 | C13: 122 | D13: 61 | E13: 78.5 | F13: =SUM(D13:E13) -> 139.5 | G13: =F13-B13 -> 73.85 | H13: =F13-C13 -> 17.5 | I13: INV26-06
A14: 18/02/26 - 28/02/26 | B14: 0 | C14: 0 | D14: 0 | E14: 0 | F14: =SUM(D14:E14) -> 0 | G14: =F14-B14 -> 0 | H14: =F14-C14 -> 0 | I14: INV26-07
A15: 28/02/26 - 07/03/26 | B15: 32.39 | C15: 54.5 | D15: 16.5 | E15: 41 | F15: =SUM(D15:E15) -> 57.5 | G15: =F15-B15 -> 25.11 | H15: =F15-C15 -> 3 | I15: INV26-08
A16: 07/03/26 - 25/03/26 | B16: 36.91 | C16: 83.5 | D16: 26.94 | E16: 34 | F16: =SUM(D16:E16) -> 60.94 | G16: =F16-B16 -> 24.03 | H16: =F16-C16 -> -22.56 | I16: INV26-09
A17: 25/03/26 - 01/04/26 | B17: 34.02 | C17: 67 | D17: 18.17 | E17: 35.5 | F17: =SUM(D17:E17) -> 53.67 | G17: =F17-B17 -> 19.65 | H17: =F17-C17 -> -13.33 | I17: INV26-10
A18: 01/04/26 - 08/04/26 | B18: 25.04 | C18: 44 | D18: 17.8 | E18: 23 | F18: =SUM(D18:E18) -> 40.8 | G18: =F18-B18 -> 15.76 | H18: =F18-C18 -> -3.2 | I18: INV26-11
A19: 08/04/26 - 29/04/26 | B19: 46.48 | C19: 90.5 | D19: 21.4 | E19: 42 | F19: =SUM(D19:E19) -> 63.4 | G19: =F19-B19 -> 16.92 | H19: =F19-C19 -> -27.1 | I19: INV26-12
... A21: 20/05/26 - 28/05/26 | B21: 38.8 | C21: 70.5 | D21: 39.6 | E21: 24.5 | F21: =SUM(D21:E21) -> 64.1 | G21: =F21-B21 -> 25.3 | H21: =F21-C21 -> -6.4 | I21: INV26-14
F22: =SUM(D22:E22) -> 0 | G22: =F22-B22 -> 0 | H22: =F22-C22 -> 0
F23: =SUM(D23:E23) -> 0 | G23: =F23-B23 -> 0 | H23: =F23-C23 -> 0
F24: =SUM(D24:E24) -> 0 | G24: =F24-B24 -> 0 | H24: =F24-C24 -> 0
F25: =SUM(D25:E25) -> 0 | G25: =F25-B25 -> 0 | H25: =F25-C25 -> 0
F26: =SUM(D26:E26) -> 0 | G26: =F26-B26 -> 0 | H26: =F26-C26 -> 0

Sheet Récap (à retoucher)
A1: Inventaire du Stock | J1: Montant du Stock | K1: =SUM(K5:K24) -> 35 | N1: Entrées et Sorties du STOCK
P2: Buy | Q2: Inv
A3: Catégorie | B3: Désignation | C3: Produit permanent | D3: Stock | E3: Stock | F3: Entrée | G3: Sortie | H3: Alerte Stock | I3: Stock Final | J3: P.U. | K3: Valeur du Stock | M3: Date | N3: Code | O3: Désignation | P3: Entrée | Q3: Comptage | R3: Vendu | S3: Vendu | T3: Prix d'achat | U3: Prix de vente
D4: Mini | E4: initial | N4: Article | R4: From HelloAsso | S4: From cash
A5: Sucré | B5: Mini BN chocolat 35g | C5: O | D5: 13 | E5: 59 | F5: =SUMIF(O:O,O5,P:P) -> 0 | G5: =SUMIFS($S:$S,$N:$N,#REF!,$O:$O,B5) -> 0 | H5: =IF(I5<D5,"Alerte","Ok") -> Ok | I5: =E5+F5-G5 -> 59 | K5: =I5*J5 -> 0 | N5: Sucré | O5: Mini BN chocolat 35g | U5: 0.5
A6: Sucré | B6: SAVANE pocket chocolat 30g | C6: O | D6: N/A | E6: 32 | F6: =SUMIF(O:O,O6,P:P) -> 0 | G6: =SUMIFS($S:$S,$N:$N,#REF!,$O:$O,B6) -> 0 | H6: =IF(I6<D6,"Alerte","Ok") -> Alerte | I6: =E6+F6-G6 -> 32 | K6: =I6*J6 -> 0 | N6: Sucré | O6: SAVANE pocket chocolat 30g | U6: 0.5
A7: Sucré | B7: Crèpes chocolat WHAOU 32g | C7: O | D7: 20 | E7: 44 | F7: =SUMIF(O:O,O7,P:P) -> 0 | G7: =SUMIFS($S:$S,$N:$N,#REF!,$O:$O,B7) -> 0 | H7: =IF(I7<D7,"Alerte","Ok") -> Ok | I7: =E7+F7-G7 -> 44 | K7: =I7*J7 -> 0 | N7: Sucré | O7: Crèpes chocolat WHAOU 32g | U7: 0.5
A8: Sucré | B8: Kinder Délice cacao 39g | C8: O | D8: 12 | E8: 26 | F8: =SUMIF(O:O,O8,P:P) -> 0 | G8: =SUMIFS($S:$S,$N:$N,#REF!,$O:$O,B8) -> 0 | H8: =IF(I8<D8,"Alerte","Ok") -> Ok | I8: =E8+F8-G8 -> 26 | K8: =I8*J8 -> 0 | N8: Sucré | O8: Kinder Délice cacao 39g | U8: 1
A9: Sucré | B9: Gauffres choco eco+ 60g | C9: O | D9: 12 | E9: 14 | F9: =SUMIF(O:O,O9,P:P) -> 0 | G9: =SUMIFS($S:$S,$N:$N,#REF!,$O:$O,B9) -> 0 | H9: =IF(I9<D9,"Alerte","Ok") -> Ok | I9: =E9+F9-G9 -> 14 | K9: =I9*J9 -> 0 | N9: Sucré | O9: Gauffres choco eco+ 60g | U9: 1
A10: Salé | B10: Chips classique Vico 27,5g | C10: O | D10: 6 | E10: 0 | F10: =SUMIF(O:O,O10,P:P) -> 0 | G10: =SUMIFS($S:$S,$N:$N,#REF!,$O:$O,B10) -> 0 | H10: =IF(I10<D10,"Alerte","Ok") -> Alerte | I10: =E10+F10-G10 -> 0 | K10: =I10*J10 -> 0 | N10: Salé | O10: Chips classique Vico 27,5g | U10: 1
A11: Sucré | B11: Dragibus 400g | C11: O | D11: 15 | E11: 74 | F11: =SUMIF(O:O,O11,P:P) -> 0 | G11: =SUMIFS($S:$S,$N:$N,#REF!,$O:$O,B11) -> 0 | H11: =IF(I11<D11,"Alerte","Ok") -> Ok | I11: =E11+F11-G11 -> 74 | K11: =I11*J11 -> 0 | N11: Sucré | O11: Dragibus 400g | U11: 0.5
A12: Sucré | B12: Miel d'Anas | C12: O | D12: 3 | E12: 7 | F12: =SUMIF(O:O,O12,P:P) -> 0 | G12: =SUMIFS($S:$S,$N:$N,#REF!,$O:$O,B12) -> 0 | H12: =IF(I12<D12,"Alerte","Ok") -> Ok | I12: =E12+F12-G12 -> 7 | J12: 5 | K12: =I12*J12 -> 35 | N12: Sucré | O12: Miel d'Anas | U12: 10
A13: Liquide | B13: Palestine Cola | C13: O | D13: 17 | E13: 1 | F13: =SUMIF(O:O,O13,P:P) -> 0 | G13: =SUMIFS($S:$S,$N:$N,#REF!,$O:$O,B13) -> 0 | H13: =IF(I13<D13,"Alerte","Ok") -> Alerte | I13: =E13+F13-G13 -> 1 | K13: =I13*J13 -> 0 | N13: Liquide | O13: Palestine Cola | U13: 1.5
A14: Liquide | B14: Palestine Lemon | C14: O | D14: 17 | E14: 0 | F14: =SUMIF(O:O,O14,P:P) -> 0 | G14: =SUMIFS($S:$S,$N:$N,#REF!,$O:$O,B14) -> 0 | H14: =IF(I14<D14,"Alerte","Ok") -> Alerte | I14: =E14+F14-G14 -> 0 | K14: =I14*J14 -> 0 | N14: Liquide | O14: Palestine Lemon | U14: 1.5
A15: Liquide | B15: Cristaline fraise | C15: O | D15: 10 | E15: 3 | F15: =SUMIF(O:O,O15,P:P) -> 24 | G15: =SUMIFS($S:$S,$N:$N,#REF!,$O:$O,B15) -> 0 | H15: =IF(I15<D15,"Alerte","Ok") -> Ok | I15: =E15+F15-G15 -> 27 | K15: =I15*J15 -> 0 | M15: 46034 | N15: Liquide | O15: Cristaline fraise | P15: 24 | U15: 1
A16: Liquide | B16: Cristaline pêche | C16: O | D16: 10 | E16: 5 | F16: =SUMIF(O:O,O16,P:P) -> 24 | G16: =SUMIFS($S:$S,$N:$N,#REF!,$O:$O,B16) -> 0 | H16: =IF(I16<D16,"Alerte","Ok") -> Ok | I16: =E16+F16-G16 -> 29 | K16: =I16*J16 -> 0 | M16: 46034 | N16: Liquide | O16: Cristaline pêche | P16: 24 | U16: 1
A17: Liquide | B17: Mecca Cola | C17: O | D17: 17 | E17: 29 | F17: =SUMIF(O:O,O17,P:P) -> 0 | G17: =SUMIFS($S:$S,$N:$N,#REF!,$O:$O,B17) -> 0 | H17: =IF(I17<D17,"Alerte","Ok") -> Ok | I17: =E17+F17-G17 -> 29 | K17: =I17*J17 -> 0 | N17: Liquide | O17: Mecca Cola | U17: 1.5
A18: Liquide | B18: Oasis PCF | C18: O | D18: 17 | E18: 19 | F18: =SUMIF(O:O,O18,P:P) -> 0 | G18: =SUMIFS($S:$S,$N:$N,#REF!,$O:$O,B18) -> 0 | H18: =IF(I18<D18,"Alerte","Ok") -> Ok | I18: =E18+F18-G18 -> 19 | K18: =I18*J18 -> 0 | N18: Liquide | O18: Oasis PCF | U18: 1.5
A19: Liquide | B19: Granini mangue | C19: O | D19: 6 | E19: 4 | F19: =SUMIF(O:O,O19,P:P) -> 0 | G19: =SUMIFS($S:$S,$N:$N,#REF!,$O:$O,B19) -> 0 | H19: =IF(I19<D19,"Alerte","Ok") -> Alerte | I19: =E19+F19-G19 -> 4 | K19: =I19*J19 -> 0 | N19: Liquide | O19: Granini mangue | U19: 2
A20: Liquide | B20: Granini orange | C20: O | D20: 6 | E20: 0 | F20: =SUMIF(O:O,O20,P:P) -> 0 | G20: =SUMIFS($S:$S,$N:$N,#REF!,$O:$O,B20) -> 0 | H20: =IF(I20<D20,"Alerte","Ok") -> Alerte | I20: =E20+F20-G20 -> 0 | K20: =I20*J20 -> 0 | N20: Liquide | O20: Granini orange | U20: 2
A21: Liquide | B21: Granini pomme | C21: O | D21: 6 | E21: 0 | F21: =SUMIF(O:O,O21,P:P) -> 0 | G21: =SUMIFS($S:$S,$N:$N,#REF!,$O:$O,B21) -> 0 | H21: =IF(I21<D21,"Alerte","Ok") -> Alerte | I21: =E21+F21-G21 -> 0 | K21: =I21*J21 -> 0 | N21: Liquide | O21: Granini pomme | U21: 2
A26: Sucré | B26: Kinder Bueno | D26: 12 | E26: 106
A27: Sucré | B27: Airwaves menthol 10g | C27: N | E27: 8
A28: Sucré | B28: Airwaves cassis 10g | C28: N | E28: 12
A29: Sucré | B29: Kinder contrefaçon | C29: N | E29: 7
A30: Liquide | B30: Orangina | C30: N | E30: 19
A31: Liquide | B31: Granini ACE | C31: N | E31: 6

Sheet Inventaires =>

Sheet INV26-1
B1: Inventaire Hebdommadaire
A2: Date | B2: 46214
A3: Heure | B3: 0.82638889
E4: SI | F4: Mouvement | H4: SF
A5: Catégorie | B5: Désignation | C5: P.U achat | D5: P.U vente | E5: Colonne 1 | F5: Achat | G5: Vendu | H5: 11/7/2026 | I5: Prix de revient | J5: CA théorique | K5: Marge
A6: Sucré | B6: Kinder Délice cacao 39g (par 10) | D6: 1 | G6: ='INV26-1'!$E6+'INV26-1'!$F6-'INV26-1'!$H6 -> 0 | I6: ='INV26-1'!$C6*'INV26-1'!$G6 -> 0 | J6: ='INV26-1'!$G6*'INV26-1'!$D6 -> 0 | K6: ='INV26-1'!$J6-'INV26-1'!$I6 -> 0
A7: Sucré | B7: Gauffres choco eco+ 60g (par 5) | D7: 1 | G7: ='INV26-1'!$E7+'INV26-1'!$F7-'INV26-1'!$H7 -> 0 | I7: ='INV26-1'!$C7*'INV26-1'!$G7 -> 0 | J7: ='INV26-1'!$G7*'INV26-1'!$D7 -> 0 | K7: ='INV26-1'!$J7-'INV26-1'!$I7 -> 0
A8: Salé | B8: Chips classique Vico 27,5g (par 6) | D8: 0.5 | G8: ='INV26-1'!$E8+'INV26-1'!$F8-'INV26-1'!$H8 -> 0 | I8: ='INV26-1'!$C8*'INV26-1'!$G8 -> 0 | J8: ='INV26-1'!$G8*'INV26-1'!$D8 -> 0 | K8: ='INV26-1'!$J8-'INV26-1'!$I8 -> 0
A9: Sucré | B9: Dragibus 20g (par 20) | D9: 0.5 | G9: ='INV26-1'!$E9+'INV26-1'!$F9-'INV26-1'!$H9 -> 0 | I9: ='INV26-1'!$C9*'INV26-1'!$G9 -> 0 | J9: ='INV26-1'!$G9*'INV26-1'!$D9 -> 0 | K9: ='INV26-1'!$J9-'INV26-1'!$I9 -> 0
A10: Sucré | B10: Kinder Bueno (par 5) | D10: 1 | G10: ='INV26-1'!$E10+'INV26-1'!$F10-'INV26-1'!$H10 -> 0 | I10: ='INV26-1'!$C10*'INV26-1'!$G10 -> 0 | J10: ='INV26-1'!$G10*'INV26-1'!$D10 -> 0 | K10: ='INV26-1'!$J10-'INV26-1'!$I10 -> 0
A11: Sucré | B11: Miel de tilleul | D11: 10 | G11: ='INV26-1'!$E11+'INV26-1'!$F11-'INV26-1'!$H11 -> 0 | I11: ='INV26-1'!$C11*'INV26-1'!$G11 -> 0 | J11: ='INV26-1'!$G11*'INV26-1'!$D11 -> 0 | K11: ='INV26-1'!$J11-'INV26-1'!$I11 -> 0
A12: Sucré | B12: Miel de forêt | D12: 10 | G12: ='INV26-1'!$E12+'INV26-1'!$F12-'INV26-1'!$H12 -> 0 | I12: ='INV26-1'!$C12*'INV26-1'!$G12 -> 0 | J12: ='INV26-1'!$G12*'INV26-1'!$D12 -> 0 | K12: ='INV26-1'!$J12-'INV26-1'!$I12 -> 0
A13: Sucré | B13: Miel d'acacia | D13: 15 | G13: ='INV26-1'!$E13+'INV26-1'!$F13-'INV26-1'!$H13 -> 0 | I13: ='INV26-1'!$C13*'INV26-1'!$G13 -> 0 | J13: ='INV26-1'!$G13*'INV26-1'!$D13 -> 0 | K13: ='INV26-1'!$J13-'INV26-1'!$I13 -> 0
A14: Sucré | B14: Miel de sarasin | D14: 15 | G14: ='INV26-1'!$E14+'INV26-1'!$F14-'INV26-1'!$H14 -> 0 | I14: ='INV26-1'!$C14*'INV26-1'!$G14 -> 0 | J14: ='INV26-1'!$G14*'INV26-1'!$D14 -> 0 | K14: ='INV26-1'!$J14-'INV26-1'!$I14 -> 0
A15: Sucré | B15: Miel de printemps | D15: 15 | G15: ='INV26-1'!$E15+'INV26-1'!$F15-'INV26-1'!$H15 -> 0 | I15: ='INV26-1'!$C15*'INV26-1'!$G15 -> 0 | J15: ='INV26-1'!$G15*'INV26-1'!$D15 -> 0 | K15: ='INV26-1'!$J15-'INV26-1'!$I15 -> 0
A16: Sucré | B16: Picks Chocolat | D16: 3 | G16: ='INV26-1'!$E16+'INV26-1'!$F16-'INV26-1'!$H16 -> 0 | I16: ='INV26-1'!$C16*'INV26-1'!$G16 -> 0 | J16: ='INV26-1'!$G16*'INV26-1'!$D16 -> 0
A17: Liquide | B17: Palestine Cola | D17: 1 | G17: ='INV26-1'!$E17+'INV26-1'!$F17-'INV26-1'!$H17 -> -50 | H17: 50 | I17: ='INV26-1'!$C17*'INV26-1'!$G17 -> 0 | J17: ='INV26-1'!$G17*'INV26-1'!$D17 -> -50 | K17: ='INV26-1'!$J17-'INV26-1'!$I17 -> -50
A18: Liquide | B18: Palestine Cola Sugar Free | D18: 1 | G18: ='INV26-1'!$E18+'INV26-1'!$F18-'INV26-1'!$H18 -> -9 | H18: 9 | I18: ='INV26-1'!$C18*'INV26-1'!$G18 -> 0 | J18: ='INV26-1'!$G18*'INV26-1'!$D18 -> -9 | K18: ='INV26-1'!$J18-'INV26-1'!$I18 -> -9
A19: Liquide | B19: Palestine Lemon | D19: 1 | G19: ='INV26-1'!$E19+'INV26-1'!$F19-'INV26-1'!$H19 -> -43 | H19: 43 | I19: ='INV26-1'!$C19*'INV26-1'!$G19 -> 0 | J19: ='INV26-1'!$G19*'INV26-1'!$D19 -> -43 | K19: ='INV26-1'!$J19-'INV26-1'!$I19 -> -43
A20: Liquide | B20: Cristaline fraise | D20: 1 | G20: ='INV26-1'!$E20+'INV26-1'!$F20-'INV26-1'!$H20 -> -43 | H20: 43 | I20: ='INV26-1'!$C20*'INV26-1'!$G20 -> 0 | J20: ='INV26-1'!$G20*'INV26-1'!$D20 -> -43 | K20: ='INV26-1'!$J20-'INV26-1'!$I20 -> -43
A21: Liquide | B21: Cristaline pêche | D21: 1 | G21: ='INV26-1'!$E21+'INV26-1'!$F21-'INV26-1'!$H21 -> -38 | H21: 38 | I21: ='INV26-1'!$C21*'INV26-1'!$G21 -> 0 | J21: ='INV26-1'!$G21*'INV26-1'!$D21 -> -38 | K21: ='INV26-1'!$J21-'INV26-1'!$I21 -> -38
A22: Liquide | B22: Oasis tropical | D22: 1 | G22: ='INV26-1'!$E22+'INV26-1'!$F22-'INV26-1'!$H22 -> -67 | H22: 67 | I22: ='INV26-1'!$C22*'INV26-1'!$G22 -> 0 | J22: ='INV26-1'!$G22*'INV26-1'!$D22 -> -67 | K22: ='INV26-1'!$J22-'INV26-1'!$I22 -> -67
A23: Liquide | B23: Orangina | D23: 1 | G23: ='INV26-1'!$E23+'INV26-1'!$F23-'INV26-1'!$H23 -> -74 | H23: 74 | I23: ='INV26-1'!$C23*'INV26-1'!$G23 -> 0 | J23: ='INV26-1'!$G23*'INV26-1'!$D23 -> -74 | K23: ='INV26-1'!$J23-'INV26-1'!$I23 -> -74
A24: Liquide | B24: Capri-Sun | D24: 1 | G24: ='INV26-1'!$E24+'INV26-1'!$F24-'INV26-1'!$H24 -> -2 | H24: 2 | I24: ='INV26-1'!$C24*'INV26-1'!$G24 -> 0 | J24: ='INV26-1'!$G24*'INV26-1'!$D24 -> -2
A25: Liquide | B25: Palestine Orange | G25: ='INV26-1'!$E25+'INV26-1'!$F25-'INV26-1'!$H25 -> -46 | H25: 46
A26: Liquide | B26: Oasis fraise framboise | G26: ='INV26-1'!$E26+'INV26-1'!$F26-'INV26-1'!$H26 -> -40 | H26: 40
A27: Liquide | B27: Oasis PCF | G27: ='INV26-1'!$E27+'INV26-1'!$F27-'INV26-1'!$H27 -> -1 | H27: 1
A28: Liquide | B28: Palestine energy drink | G28: ='INV26-1'!$E28+'INV26-1'!$F28-'INV26-1'!$H28 -> -25 | H28: 25
A29: Liquide | B29: Cristaline gazeux | G29: ='INV26-1'!$E29+'INV26-1'!$F29-'INV26-1'!$H29 -> -14 | H29: 14
